qt_desktop_translate/__init__.py
qt_desktop_translate/desktop_lrelease.py
qt_desktop_translate/desktop_lupdate.py
qt_desktop_translate-1.1.dist-info/LICENSE
qt_desktop_translate-1.1.dist-info/METADATA
qt_desktop_translate-1.1.dist-info/WHEEL
qt_desktop_translate-1.1.dist-info/entry_points.txt
qt_desktop_translate-1.1.dist-info/top_level.txt
qt_desktop_translate-1.1.dist-info/RECORD
